sentry_plugin_alert_dingtalk/__init__.py
sentry_plugin_alert_dingtalk/forms.py
sentry_plugin_alert_dingtalk/plugin.py
sentry_plugin_alert_dingtalk/template.py
sentry_plugin_alert_dingtalk-1.0.4.dist-info/LICENSE
sentry_plugin_alert_dingtalk-1.0.4.dist-info/METADATA
sentry_plugin_alert_dingtalk-1.0.4.dist-info/WHEEL
sentry_plugin_alert_dingtalk-1.0.4.dist-info/entry_points.txt
sentry_plugin_alert_dingtalk-1.0.4.dist-info/top_level.txt
sentry_plugin_alert_dingtalk-1.0.4.dist-info/RECORD
